{
    "@class": "com.kony.gen.viz.model.component.KVizImage2",
    "DNDConfig": null,
    "__parentReadjusting__": false,
    "_base64_": null,
    "_height_": {
        "type": "string",
        "value": "25dp"
    },
    "_left_": {
        "type": "string",
        "value": "0dp"
    },
    "_margin_": [
        0,
        0,
        0,
        0
    ],
    "_padding_": [
        0,
        0,
        0,
        0
    ],
    "_skin_": "se67590e9be147878cf72135a3104587",
    "_src_": "arrowright.png",
    "_top_": {
        "type": "string",
        "value": "3dp"
    },
    "_width_": {
        "type": "string",
        "value": "25dp"
    },
    "canUpdateUI": true,
    "centery": {
        "type": "string",
        "value": "49.84%"
    },
    "containerweight": 100,
    "context": {
        "channel": "mobile",
        "formID": "frmUserKA",
        "platform": "android",
        "templateType": "forms",
        "topLevelBox": null
    },
    "id": "imgNext1",
    "ide_onTouchStart": "AS_Image_g00919c99de643e9a6b151f6f922f53e",
    "imagescalemode": 1,
    "info": null,
    "invokedProperty": "src",
    "isvisible": true,
    "kuid": "bc069083136f430f853ed86a071d32e4",
    "name": "kony.ui.Image2",
    "parent": "flxDetail1",
    "pf": "frmUserKA",
    "srcType": 1,
    "wType": "Image",
    "widgetalignment": 5,
    "zindex": 1
}